MANIFEST.in
PLANNING.txt
requirements.txt
setup.py
ecosynth/LICENSE.md
ecosynth/__init__.py
ecosynth/__main__.py
ecosynth.egg-info/PKG-INFO
ecosynth.egg-info/SOURCES.txt
ecosynth.egg-info/dependency_links.txt
ecosynth.egg-info/requires.txt
ecosynth.egg-info/top_level.txt
ecosynth/acquire/__init__.py
ecosynth/acquire/utilities.py
ecosynth/datasets/__init__.py
ecosynth/datasets/base.py
ecosynth/generate/__init__.py
ecosynth/generate/utilities.py
ecosynth/generate/tests/__init__.py
ecosynth/generate/tests/test_interpolate_gps_for_cams.py
ecosynth/gui/__init__.py
ecosynth/gui/webapp.py
ecosynth/gui/static/__init__.py
ecosynth/gui/static/css
ecosynth/gui/static/fonts
ecosynth/gui/static/html
ecosynth/gui/static/js
ecosynth/gui/static/css/__init__.py
ecosynth/gui/static/css/bootstrap-theme.css
ecosynth/gui/static/css/bootstrap-theme.css.map
ecosynth/gui/static/css/bootstrap-theme.min.css
ecosynth/gui/static/css/bootstrap.css
ecosynth/gui/static/css/bootstrap.css.map
ecosynth/gui/static/css/bootstrap.min.css
ecosynth/gui/static/css/navbar.css
ecosynth/gui/static/css/styles.css
ecosynth/gui/static/fonts/__init__.py
ecosynth/gui/static/fonts/glyphicons-halflings-regular.eot
ecosynth/gui/static/fonts/glyphicons-halflings-regular.svg
ecosynth/gui/static/fonts/glyphicons-halflings-regular.ttf
ecosynth/gui/static/fonts/glyphicons-halflings-regular.woff
ecosynth/gui/static/html/__init__.py
ecosynth/gui/static/html/form.html
ecosynth/gui/static/html/index.html
ecosynth/gui/static/html/postprocess_form.html
ecosynth/gui/static/html/share_form.html
ecosynth/gui/static/html/themes.html
ecosynth/gui/static/images/logo.png
ecosynth/gui/static/js/__init__.py
ecosynth/gui/static/js/bootstrap.js
ecosynth/gui/static/js/bootstrap.min.js
ecosynth/gui/static/js/jquery.min.js
ecosynth/postprocess/CloudRasterizer.py
ecosynth/postprocess/__init__.py
ecosynth/postprocess/io.py
ecosynth/postprocess/run.py
ecosynth/postprocess/transforms.py
ecosynth/postprocess/tests/__init__.py
ecosynth/postprocess/tests/test_georef.py
ecosynth/postprocess/tests/test_load_ply.py
ecosynth/share/__init__.py
ecosynth/share/ezid.py
ecosynth/share/utilities.py