Metadata-Version: 1.0
Name: ecosynth
Version: 0.2.4
Summary: Ecosynth Processing Library
Home-page: http://www.ecosynth.org
Author: Ecosynth Lab, UMBC
Author-email: willb2@umbc.edu
License: Creative Commons Attribution 4.0 International
Keywords: point-clouds CV ecology
Platform: UNKNOWN
